ayon_api/__init__.py
ayon_api/_api.py
ayon_api/constants.py
ayon_api/entity_hub.py
ayon_api/events.py
ayon_api/exceptions.py
ayon_api/graphql.py
ayon_api/graphql_queries.py
ayon_api/operations.py
ayon_api/server_api.py
ayon_api/typing.py
ayon_api/utils.py
ayon_api/version.py
ayon_api-0.0.1b3.dist-info/LICENSE
ayon_api-0.0.1b3.dist-info/METADATA
ayon_api-0.0.1b3.dist-info/WHEEL
ayon_api-0.0.1b3.dist-info/top_level.txt
ayon_api-0.0.1b3.dist-info/RECORD
